{
    "Climatizaci\u00f3n": {
        "category": 1652,
        "sub_items": [],
        "url": "/climatizacion"
    },
    "Muebles": {
        "category": 1555,
        "sub_items": [],
        "url": "/muebles"
    },
    "Herramientas": {
        "category": 1278,
        "sub_items": [],
        "url": "/herramientas"
    },
    "Electrodom\u00e9sticos": {
        "category": 1651,
        "sub_items": [],
        "url": "/electrodomesticos"
    },
    "Tecnolog\u00eda": {
        "category": 1686,
        "sub_items": [],
        "url": "/tecnologia"
    },
    "Aire Libre y Deportes": {
        "category": 4260,
        "sub_items": [],
        "url": "/aire-libre-y-deportes"
    },
    "Beb\u00e9s y Ni\u00f1os": {
        "category": 227,
        "sub_items": [],
        "url": "/bebes-y-ninos"
    },
    "Calefacci\u00f3n": {
        "category": 1557,
        "sub_items": [],
        "url": "/climatizacion/calefaccion"
    },
    "Calefacci\u00f3n a Gas": {
        "category": 1443,
        "sub_items": [],
        "url": "/climatizacion/calefaccion/calefaccion-a-gas"
    },
    "Calefacci\u00f3n El\u00e9ctrica": {
        "category": 1445,
        "sub_items": [],
        "url": "/climatizacion/calefaccion/calefaccion--electrica"
    },
    "Calefacci\u00f3n a Le\u00f1a": {
        "category": 1656,
        "sub_items": [],
        "url": "/climatizacion/calefaccion/calefaccion-a-lena"
    },
    "Aire Acondicionado": {
        "category": 4120,
        "sub_items": [],
        "url": "/climatizacion/aire-acondicionado"
    },
    "Ventilaci\u00f3n": {
        "category": 1418,
        "sub_items": [],
        "url": "/climatizacion/ventilacion"
    },
    "Muebles de Dormitorio": {
        "category": 1873,
        "sub_items": [],
        "url": "/muebles/muebles-de-dormitorio"
    },
    "Muebles Living": {
        "category": 4261,
        "sub_items": [],
        "url": "/muebles/muebles-living"
    },
    "Muebles Comedor": {
        "category": 4262,
        "sub_items": [],
        "url": "/muebles/muebles-comedor"
    },
    "Muebles Cocina": {
        "category": 4263,
        "sub_items": [],
        "url": "/muebles/muebles-cocina"
    },
    "Colchones y Sommier": {
        "category": 1769,
        "sub_items": [],
        "url": "/muebles/colchones-y-sommier"
    },
    "Muebles de Jard\u00edn": {
        "category": 1518,
        "sub_items": [],
        "url": "/muebles/muebles-de-jardin"
    },
    "Muebles de Escritorio": {
        "category": 4264,
        "sub_items": [],
        "url": "/muebles/muebles-de-escritorio"
    },
    "Organizadores": {
        "category": 1623,
        "sub_items": [],
        "url": "/muebles/organizadores"
    },
    "Hidrolavadoras": {
        "category": 1522,
        "sub_items": [],
        "url": "/herramientas/hidrolavadoras"
    },
    "Motosierras": {
        "category": 1513,
        "sub_items": [],
        "url": "/herramientas/motosierras"
    },
    "Cortadoras de C\u00e9sped": {
        "category": 1777,
        "sub_items": [],
        "url": "/herramientas/cortadoras-de-cesped"
    },
    "Desmalezadoras": {
        "category": 1779,
        "sub_items": [],
        "url": "/herramientas/desmalezadoras"
    },
    "Herramientas de Mano": {
        "category": 4265,
        "sub_items": [],
        "url": "/herramientas/herramientas-de-mano"
    },
    "Escaleras": {
        "category": 1610,
        "sub_items": [],
        "url": "/herramientas/escaleras"
    },
    "Cubiertas": {
        "category": 1535,
        "sub_items": [],
        "url": "/herramientas/cubiertas"
    },
    "Soldadoras": {
        "category": 1515,
        "sub_items": [],
        "url": "/herramientas/soldadoras"
    },
    "Compresores": {
        "category": 1510,
        "sub_items": [],
        "url": "/herramientas/compresores"
    },
    "Bater\u00edas": {
        "category": 1314,
        "sub_items": [],
        "url": "/herramientas/baterias"
    },
    "Lavavajillas": {
        "category": 1467,
        "sub_items": [],
        "url": "/electrodomesticos/lavavajillas"
    },
    "Lavado": {
        "category": 1657,
        "sub_items": [],
        "url": "/electrodomesticos/lavado"
    },
    "Lavarropas": {
        "category": 1464,
        "sub_items": [],
        "url": "/electrodomesticos/lavado/lavarropas"
    },
    "Secarropas": {
        "category": 1466,
        "sub_items": [],
        "url": "/electrodomesticos/lavado/secarropas"
    },
    "Campanas y Purificadores": {
        "category": 2858,
        "sub_items": [],
        "url": "/electrodomesticos/campanas-y-purificadores"
    },
    "Termotanques y Calefones": {
        "category": 1663,
        "sub_items": [],
        "url": "/electrodomesticos/termotanques-y-calefones"
    },
    "Termotanques": {
        "category": 1604,
        "sub_items": [],
        "url": "/electrodomesticos/termotanques-y-calefones/termotanques"
    },
    "Calefones": {
        "category": 1664,
        "sub_items": [],
        "url": "/electrodomesticos/termotanques-y-calefones/calefones"
    },
    "Peque\u00f1os Electrodom\u00e9sticos": {
        "category": 2800,
        "sub_items": [],
        "url": "/electrodomesticos/pequenos-electrodomesticos"
    },
    "Cuidado Personal y Salud": {
        "category": 2801,
        "sub_items": [],
        "url": "/electrodomesticos/pequenos-electrodomesticos/cuidado-personal-y-salud"
    },
    "Art\u00edculos del Hogar": {
        "category": 4266,
        "sub_items": [],
        "url": "/electrodomesticos/pequenos-electrodomesticos/articulos-del-hogar"
    },
    "Art\u00edculos de Cocina": {
        "category": 4267,
        "sub_items": [],
        "url": "/electrodomesticos/pequenos-electrodomesticos/articulos-de-cocina"
    },
    "Hornos y Cocinas": {
        "category": 4268,
        "sub_items": [],
        "url": "/electrodomesticos/hornos-y-cocinas"
    },
    "Cocinas": {
        "category": 1471,
        "sub_items": [],
        "url": "/electrodomesticos/hornos-y-cocinas/cocinas"
    },
    "Hornos El\u00e9ctricos": {
        "category": 1659,
        "sub_items": [],
        "url": "/electrodomesticos/hornos-y-cocinas/hornos-electricos"
    },
    "Anafes": {
        "category": 1473,
        "sub_items": [],
        "url": "/electrodomesticos/hornos-y-cocinas/anafes"
    },
    "Microondas": {
        "category": 1474,
        "sub_items": [],
        "url": "/electrodomesticos/hornos-y-cocinas/microondas"
    },
    "Parrillas": {
        "category": 1521,
        "sub_items": [],
        "url": "/electrodomesticos/hornos-y-cocinas/parrillas"
    },
    "Heladeras, Freezers y Cavas": {
        "category": 4080,
        "sub_items": [],
        "url": "/electrodomesticos/heladeras-freezers-y-cavas"
    },
    "Heladeras Con Freezer": {
        "category": 1857,
        "sub_items": [],
        "url": "/electrodomesticos/heladeras-freezers-y-cavas/heladeras-con-freezer"
    },
    "Heladeras Sin Freezer": {
        "category": 1858,
        "sub_items": [],
        "url": "/electrodomesticos/heladeras-freezers-y-cavas/heladeras-sin-freezer"
    },
    "Exhibidoras": {
        "category": 1479,
        "sub_items": [],
        "url": "/electrodomesticos/heladeras-freezers-y-cavas/exhibidoras"
    },
    "Cavas": {
        "category": 1478,
        "sub_items": [],
        "url": "/electrodomesticos/heladeras-freezers-y-cavas/cavas"
    },
    "Freezers": {
        "category": 1556,
        "sub_items": [],
        "url": "/electrodomesticos/heladeras-freezers-y-cavas/freezers"
    },
    "Inform\u00e1tica": {
        "category": 1689,
        "sub_items": [],
        "url": "/tecnologia/informatica"
    },
    "Monitores": {
        "category": 1302,
        "sub_items": [],
        "url": "/tecnologia/informatica/monitores"
    },
    "Impresoras": {
        "category": 1281,
        "sub_items": [],
        "url": "/tecnologia/informatica/impresoras"
    },
    "PC y Notebooks": {
        "category": 4269,
        "sub_items": [],
        "url": "/tecnologia/informatica/pc-y-notebooks"
    },
    "Tablets": {
        "category": 1350,
        "sub_items": [],
        "url": "/tecnologia/informatica/tablets"
    },
    "Accesorios Inform\u00e1ticos": {
        "category": 4270,
        "sub_items": [],
        "url": "/tecnologia/informatica/accesorios-informaticos"
    },
    "TV y Accesorios": {
        "category": 4271,
        "sub_items": [],
        "url": "/tecnologia/tv--y-accesorios"
    },
    "TV": {
        "category": 4272,
        "sub_items": [],
        "url": "/tecnologia/tv--y-accesorios/tv"
    },
    "Accesorios TV": {
        "category": 4273,
        "sub_items": [],
        "url": "/tecnologia/tv--y-accesorios/accesorios-tv"
    },
    "Soportes": {
        "category": 1345,
        "sub_items": [],
        "url": "/tecnologia/tv--y-accesorios/soportes"
    },
    "Audio": {
        "category": 1217,
        "sub_items": [],
        "url": "/tecnologia/audio"
    },
    "Auriculares": {
        "category": 1206,
        "sub_items": [],
        "url": "/tecnologia/gaming/auriculares"
    },
    "Parlantes": {
        "category": 1311,
        "sub_items": [],
        "url": "/tecnologia/audio/parlantes"
    },
    "Audio para Autos": {
        "category": 1697,
        "sub_items": [],
        "url": "/tecnologia/audio/audio-para-autos"
    },
    "Micr\u00f3fonos": {
        "category": 1299,
        "sub_items": [],
        "url": "/tecnologia/audio/microfonos"
    },
    "Minicomponentes": {
        "category": 1383,
        "sub_items": [],
        "url": "/tecnologia/audio/minicomponentes"
    },
    "Radios": {
        "category": 1331,
        "sub_items": [],
        "url": "/tecnologia/audio/radios"
    },
    "Gaming": {
        "category": 1548,
        "sub_items": [],
        "url": "/tecnologia/gaming"
    },
    "Consolas y Videogames": {
        "category": 4274,
        "sub_items": [],
        "url": "/tecnologia/gaming/consolas-y-videos"
    },
    "Teclados, Mouse y Pads": {
        "category": 4275,
        "sub_items": [],
        "url": "/tecnologia/gaming/tecladosmouse-y-pads"
    },
    "Joystics y Accesorios": {
        "category": 4276,
        "sub_items": [],
        "url": "/tecnologia/gaming/joystics-y-accesorios"
    },
    "Sillas Gamer": {
        "category": 2650,
        "sub_items": [],
        "url": "/tecnologia/gaming/sillas-gamer"
    },
    "Fotograf\u00eda y Videoc\u00e1maras": {
        "category": 4277,
        "sub_items": [],
        "url": "/tecnologia/fotografia-y-video-camaras"
    },
    "Fotograf\u00eda y Video": {
        "category": 4278,
        "sub_items": [],
        "url": "/tecnologia/fotografia-y-video-camaras/fotografia-y-video"
    },
    "C\u00e1maras de Seguridad": {
        "category": 1486,
        "sub_items": [],
        "url": "/tecnologia/fotografia-y-video-camaras/camaras-de-seguridad"
    },
    "C\u00e1maras Deportivas": {
        "category": 1230,
        "sub_items": [],
        "url": "/tecnologia/fotografia-y-video-camaras/camaras-deportivas"
    },
    "Accesorios": {
        "category": 951,
        "sub_items": [],
        "url": "/tecnologia/fotografia-y-video-camaras/accesorios"
    },
    "Celulares": {
        "category": 1233,
        "sub_items": [],
        "url": "/tecnologia/celulares"
    },
    "Tel\u00e9fono Fijo": {
        "category": 4279,
        "sub_items": [],
        "url": "/tecnologia/telefono-fijo"
    },
    "Relojes y Smartwatch": {
        "category": 4280,
        "sub_items": [],
        "url": "/tecnologia/relojes-y-smartwatch"
    },
    "Rodados": {
        "category": 4281,
        "sub_items": [],
        "url": "/aire-libre-y-deportes/rodados"
    },
    "Camping": {
        "category": 1553,
        "sub_items": [],
        "url": "/aire-libre-y-deportes/camping"
    },
    "Piletas": {
        "category": 1519,
        "sub_items": [],
        "url": "/aire-libre-y-deportes/piletas"
    },
    "Fitness Deportes": {
        "category": 4282,
        "sub_items": [],
        "url": "/aire-libre-y-deportes/fitness-deportes"
    },
    "T\u00e9rmicos": {
        "category": 4283,
        "sub_items": [],
        "url": "/aire-libre-y-deportes/termicos"
    },
    "Equipaje": {
        "category": 4284,
        "sub_items": [],
        "url": "/aire-libre-y-deportes/equipaje"
    },
    "Primera Infancia": {
        "category": 2684,
        "sub_items": [],
        "url": "/bebes-y-ninos/primera-infancia"
    },
    "Escolares": {
        "category": 4285,
        "sub_items": [],
        "url": "/bebes-y-ninos/escolares"
    },
    "Juguetes": {
        "category": 1530,
        "sub_items": [],
        "url": "/bebes-y-ninos/juguetes"
    }
}